celeref_lang/__init__.py
celeref_lang/main.py
celeref_lang/version.py
celeref_lang/functions/__init__.py
celeref_lang/functions/math.py
celeref_lang/functions/op.py
celeref_lang/schema/schema.json
celeref_lang/statements/__init__.py
celeref_lang/statements/at.py
celeref_lang/statements/call.py
celeref_lang/statements/dot-call.py
celeref_lang/statements/dot.py
celeref_lang/statements/if-else.py
celeref_lang/statements/load.py
celeref_lang/statements/loop.py
celeref_lang/statements/move.py
celeref_lang/statements/print.py
celeref_lang/statements/save.py
celeref_lang/statements/set.py
celeref_lang/statements/state.py
celeref_lang/statements/switch.py
celeref_lang-0.0.7.dist-info/METADATA
celeref_lang-0.0.7.dist-info/WHEEL
celeref_lang-0.0.7.dist-info/entry_points.txt
celeref_lang-0.0.7.dist-info/top_level.txt
celeref_lang-0.0.7.dist-info/RECORD
