Metadata-Version: 2.1
Name: celeref-lang
Version: 0.0.7
Summary: A interpreter for celeref programming language
Home-page: https://github.com/dipu-bd/celeref-lang
Author: Sudipto Chandra
Author-email: dipu.sudipta@gmail.com
License: UNKNOWN
Keywords: interpreter language celeref
Platform: UNKNOWN
Classifier: Development Status :: 3 - Alpha
Classifier: Environment :: Console
Classifier: Intended Audience :: Developers
Classifier: License :: Free For Educational Use
Classifier: Natural Language :: English
Classifier: Operating System :: OS Independent
Classifier: Programming Language :: Python
Classifier: Programming Language :: Python :: 3
Classifier: Programming Language :: Python :: 3.6
Classifier: Programming Language :: Python :: 3.7
Classifier: Programming Language :: Python :: 3.8
Classifier: Topic :: Software Development :: Libraries :: Python Modules
Requires-Dist: jsonschema
Requires-Dist: requests
